{
  "f": {
    "passengerRecords": [
      {
        "recordID": "Zgyi855646",
        "passenger": {
          "firstName": "HXzds",
          "lastName": "FAl",
          "address": "EQGLHQdw",
          "phoneNumber": "8576881598"
        },
        "destination": "NewDelhi",
        "flightClass": "business",
        "dateOfFlight": "2016.10.23 20:22"
      }
    ]
  },
  "g": {
    "passengerRecords": [
      {
        "recordID": "MGME065631",
        "passenger": {
          "firstName": "hDEpL",
          "lastName": "gUb",
          "address": "bXOOJiAT",
          "phoneNumber": "7033383195"
        },
        "destination": "NewDelhi",
        "flightClass": "business",
        "dateOfFlight": "2016.10.23 20:22"
      },
      {
        "recordID": "bMiL436033",
        "passenger": {
          "firstName": "ugVfo",
          "lastName": "GIt",
          "address": "GtniPAWp",
          "phoneNumber": "3203478625"
        },
        "destination": "NewDelhi",
        "flightClass": "business",
        "dateOfFlight": "2016.10.23 20:22"
      },
      {
        "recordID": "Nlbo354792",
        "passenger": {
          "firstName": "PcMCK",
          "lastName": "GDX",
          "address": "EzQDdfqK",
          "phoneNumber": "3199419299"
        },
        "destination": "NewDelhi",
        "flightClass": "business",
        "dateOfFlight": "2016.10.23 20:22"
      }
    ]
  },
  "d": {
    "passengerRecords": [
      {
        "recordID": "CIxw158435",
        "passenger": {
          "firstName": "YnSZf",
          "lastName": "dMY",
          "address": "McXcsGbc",
          "phoneNumber": "6157124356"
        },
        "destination": "NewDelhi",
        "flightClass": "economy",
        "dateOfFlight": "2016.10.23 20:22"
      },
      {
        "recordID": "cJTW146515",
        "passenger": {
          "firstName": "XdDri",
          "lastName": "dNf",
          "address": "yQNyTHRl",
          "phoneNumber": "9235236728"
        },
        "destination": "NewDelhi",
        "flightClass": "fit",
        "dateOfFlight": "2016.10.23 20:22"
      }
    ]
  },
  "e": {
    "passengerRecords": [
      {
        "recordID": "JATu224788",
        "passenger": {
          "firstName": "diGXI",
          "lastName": "eal",
          "address": "GrfrCNmh",
          "phoneNumber": "3533901618"
        },
        "destination": "Montreal",
        "flightClass": "fit",
        "dateOfFlight": "2016.11.18 10:10"
      },
      {
        "recordID": "nvDO345696",
        "passenger": {
          "firstName": "gtwFK",
          "lastName": "Esw",
          "address": "NfxghJBV",
          "phoneNumber": "9816585604"
        },
        "destination": "Montreal",
        "flightClass": "business",
        "dateOfFlight": "2016.11.18 10:10"
      }
    ]
  },
  "b": {
    "passengerRecords": [
      {
        "recordID": "cZmM230417",
        "passenger": {
          "firstName": "dKXtr",
          "lastName": "bJD",
          "address": "iCfIWMLk",
          "phoneNumber": "0563997683"
        },
        "destination": "NewDelhi",
        "flightClass": "fit",
        "dateOfFlight": "2016.10.23 20:22"
      },
      {
        "recordID": "vfLy067280",
        "passenger": {
          "firstName": "RjynN",
          "lastName": "BOv",
          "address": "vXGTAnok",
          "phoneNumber": "4746689570"
        },
        "destination": "Montreal",
        "flightClass": "business",
        "dateOfFlight": "2016.11.18 10:10"
      },
      {
        "recordID": "pKiM348905",
        "passenger": {
          "firstName": "bDQVQ",
          "lastName": "Bbl",
          "address": "jhCkeLFp",
          "phoneNumber": "4956533618"
        },
        "destination": "NewDelhi",
        "flightClass": "fit",
        "dateOfFlight": "2016.10.23 20:22"
      }
    ]
  },
  "c": {
    "passengerRecords": [
      {
        "recordID": "muFs219039",
        "passenger": {
          "firstName": "EOFqG",
          "lastName": "cJK",
          "address": "upExXyco",
          "phoneNumber": "7626458942"
        },
        "destination": "Montreal",
        "flightClass": "business",
        "dateOfFlight": "2016.08.08 07:07"
      }
    ]
  },
  "a": {
    "passengerRecords": [
      {
        "recordID": "uzHq368828",
        "passenger": {
          "firstName": "vtfmk",
          "lastName": "aup",
          "address": "TVkiwLXf",
          "phoneNumber": "2306334006"
        },
        "destination": "NewDelhi",
        "flightClass": "economy",
        "dateOfFlight": "2016.10.23 20:22"
      },
      {
        "recordID": "rKvW634885",
        "passenger": {
          "firstName": "asdfjka",
          "lastName": "asdf3",
          "address": "23ewd",
          "phoneNumber": "23we2432"
        },
        "destination": "Montreal",
        "flightClass": "business",
        "dateOfFlight": "2016.11.18 10:10"
      },
      {
        "recordID": "PQSO004803",
        "passenger": {
          "firstName": "ustlU",
          "lastName": "aey",
          "address": "gGJXWeBu",
          "phoneNumber": "2294035521"
        },
        "destination": "Montreal",
        "flightClass": "economy",
        "dateOfFlight": "2016.11.18 10:10"
      }
    ]
  },
  "n": {
    "passengerRecords": [
      {
        "recordID": "rUGx003789",
        "passenger": {
          "firstName": "odFmX",
          "lastName": "nci",
          "address": "iXobRkbs",
          "phoneNumber": "8991147118"
        },
        "destination": "NewDelhi",
        "flightClass": "business",
        "dateOfFlight": "2016.10.23 20:22"
      },
      {
        "recordID": "rTfK424264",
        "passenger": {
          "firstName": "oJPsl",
          "lastName": "NuG",
          "address": "RwTaHKSh",
          "phoneNumber": "0799784029"
        },
        "destination": "Montreal",
        "flightClass": "business",
        "dateOfFlight": "2016.11.18 10:10"
      }
    ]
  },
  "o": {
    "passengerRecords": [
      {
        "recordID": "Ambo915993",
        "passenger": {
          "firstName": "tNgop",
          "lastName": "oel",
          "address": "PbyqAYVC",
          "phoneNumber": "5010864359"
        },
        "destination": "NewDelhi",
        "flightClass": "fit",
        "dateOfFlight": "2016.10.23 20:22"
      },
      {
        "recordID": "QpDQ138108",
        "passenger": {
          "firstName": "NXdmj",
          "lastName": "Owk",
          "address": "DAqSassm",
          "phoneNumber": "8317367994"
        },
        "destination": "NewDelhi",
        "flightClass": "economy",
        "dateOfFlight": "2016.10.23 20:22"
      },
      {
        "recordID": "XAIH016187",
        "passenger": {
          "firstName": "otPWk",
          "lastName": "Ooi",
          "address": "OBMXtIcn",
          "phoneNumber": "4999549094"
        },
        "destination": "Montreal",
        "flightClass": "business",
        "dateOfFlight": "2016.11.18 10:10"
      }
    ]
  },
  "l": {
    "passengerRecords": [
      {
        "recordID": "MRzJ779138",
        "passenger": {
          "firstName": "bWPUR",
          "lastName": "Lex",
          "address": "TFYXrYIo",
          "phoneNumber": "7370463515"
        },
        "destination": "Montreal",
        "flightClass": "business",
        "dateOfFlight": "2016.11.18 10:10"
      },
      {
        "recordID": "txRo530708",
        "passenger": {
          "firstName": "PtxqU",
          "lastName": "Ldi",
          "address": "eVSTZyRa",
          "phoneNumber": "6754624734"
        },
        "destination": "NewDelhi",
        "flightClass": "fit",
        "dateOfFlight": "2016.10.23 20:22"
      },
      {
        "recordID": "cpSk823117",
        "passenger": {
          "firstName": "Iukul",
          "lastName": "lor",
          "address": "RPwEdWbi",
          "phoneNumber": "7347460398"
        },
        "destination": "NewDelhi",
        "flightClass": "business",
        "dateOfFlight": "2016.10.23 20:22"
      }
    ]
  },
  "m": {
    "passengerRecords": [
      {
        "recordID": "TaWK662441",
        "passenger": {
          "firstName": "cfXWA",
          "lastName": "MVY",
          "address": "NPSsHPGM",
          "phoneNumber": "7617546761"
        },
        "destination": "NewDelhi",
        "flightClass": "fit",
        "dateOfFlight": "2016.10.23 20:22"
      },
      {
        "recordID": "qclb203338",
        "passenger": {
          "firstName": "wcOEU",
          "lastName": "MEq",
          "address": "HxUcFhdi",
          "phoneNumber": "2821402110"
        },
        "destination": "NewDelhi",
        "flightClass": "fit",
        "dateOfFlight": "2016.10.23 20:22"
      }
    ]
  },
  "j": {
    "passengerRecords": [
      {
        "recordID": "AYsy595292",
        "passenger": {
          "firstName": "kRIfN",
          "lastName": "jCq",
          "address": "RgufGUSu",
          "phoneNumber": "3974737994"
        },
        "destination": "Montreal",
        "flightClass": "business",
        "dateOfFlight": "2016.11.18 10:10"
      },
      {
        "recordID": "BJWs078345",
        "passenger": {
          "firstName": "kDcYc",
          "lastName": "jTM",
          "address": "lxcHTUio",
          "phoneNumber": "4856913811"
        },
        "destination": "NewDelhi",
        "flightClass": "business",
        "dateOfFlight": "2016.10.23 20:22"
      }
    ]
  },
  "h": {
    "passengerRecords": [
      {
        "recordID": "GFNl175509",
        "passenger": {
          "firstName": "LuEii",
          "lastName": "hED",
          "address": "bxCjfFdD",
          "phoneNumber": "3758679031"
        },
        "destination": "Montreal",
        "flightClass": "economy",
        "dateOfFlight": "2016.11.18 10:10"
      }
    ]
  },
  "i": {
    "passengerRecords": [
      {
        "recordID": "msyV645196",
        "passenger": {
          "firstName": "MUIEE",
          "lastName": "IuW",
          "address": "KbpUMZOB",
          "phoneNumber": "5229119199"
        },
        "destination": "Montreal",
        "flightClass": "business",
        "dateOfFlight": "2016.11.18 10:10"
      },
      {
        "recordID": "cDZq611827",
        "passenger": {
          "firstName": "OQOum",
          "lastName": "iQA",
          "address": "jBjZgiQF",
          "phoneNumber": "9679487226"
        },
        "destination": "NewDelhi",
        "flightClass": "business",
        "dateOfFlight": "2016.10.23 20:22"
      },
      {
        "recordID": "ZTOe934923",
        "passenger": {
          "firstName": "NNXqj",
          "lastName": "IbH",
          "address": "KnIIrJyb",
          "phoneNumber": "7750511284"
        },
        "destination": "NewDelhi",
        "flightClass": "economy",
        "dateOfFlight": "2016.10.23 20:22"
      },
      {
        "recordID": "kpvH721258",
        "passenger": {
          "firstName": "aHMZC",
          "lastName": "Iob",
          "address": "qgTFfsZU",
          "phoneNumber": "4406170708"
        },
        "destination": "NewDelhi",
        "flightClass": "business",
        "dateOfFlight": "2016.10.23 20:22"
      }
    ]
  },
  "w": {
    "passengerRecords": [
      {
        "recordID": "iGbs096117",
        "passenger": {
          "firstName": "bbEkz",
          "lastName": "wQk",
          "address": "QXKedfMn",
          "phoneNumber": "6646075232"
        },
        "destination": "NewDelhi",
        "flightClass": "business",
        "dateOfFlight": "2016.10.23 20:22"
      },
      {
        "recordID": "RdPP356946",
        "passenger": {
          "firstName": "OTLLV",
          "lastName": "WbF",
          "address": "pLodINEo",
          "phoneNumber": "9115588271"
        },
        "destination": "NewDelhi",
        "flightClass": "business",
        "dateOfFlight": "2016.10.23 20:22"
      }
    ]
  },
  "v": {
    "passengerRecords": [
      {
        "recordID": "soWx227383",
        "passenger": {
          "firstName": "hjeIq",
          "lastName": "VRy",
          "address": "nPSmtoSi",
          "phoneNumber": "4255320058"
        },
        "destination": "NewDelhi",
        "flightClass": "fit",
        "dateOfFlight": "2016.10.23 20:22"
      }
    ]
  },
  "u": {
    "passengerRecords": [
      {
        "recordID": "roGx977727",
        "passenger": {
          "firstName": "eRhPJ",
          "lastName": "UPD",
          "address": "dTyXqryP",
          "phoneNumber": "5074487962"
        },
        "destination": "Montreal",
        "flightClass": "economy",
        "dateOfFlight": "2016.11.18 10:10"
      },
      {
        "recordID": "hPJq561498",
        "passenger": {
          "firstName": "DymuH",
          "lastName": "ukf",
          "address": "XDxqkwRJ",
          "phoneNumber": "4914393500"
        },
        "destination": "Montreal",
        "flightClass": "business",
        "dateOfFlight": "2016.11.18 10:10"
      }
    ]
  },
  "t": {
    "passengerRecords": [
      {
        "recordID": "qINV032036",
        "passenger": {
          "firstName": "tDPYE",
          "lastName": "TnW",
          "address": "byBxygrH",
          "phoneNumber": "5000307939"
        },
        "destination": "NewDelhi",
        "flightClass": "economy",
        "dateOfFlight": "2016.10.23 20:22"
      },
      {
        "recordID": "raMm199343",
        "passenger": {
          "firstName": "ckWmv",
          "lastName": "tMF",
          "address": "ZujVEOPA",
          "phoneNumber": "3774253436"
        },
        "destination": "NewDelhi",
        "flightClass": "economy",
        "dateOfFlight": "2016.10.23 20:22"
      },
      {
        "recordID": "etiz297972",
        "passenger": {
          "firstName": "yJqHk",
          "lastName": "TxB",
          "address": "scBCJsKL",
          "phoneNumber": "3687441653"
        },
        "destination": "NewDelhi",
        "flightClass": "economy",
        "dateOfFlight": "2016.10.23 20:22"
      }
    ]
  },
  "s": {
    "passengerRecords": [
      {
        "recordID": "zcpK663130",
        "passenger": {
          "firstName": "PjkLt",
          "lastName": "svb",
          "address": "qCfMqZHZ",
          "phoneNumber": "3219330254"
        },
        "destination": "NewDelhi",
        "flightClass": "economy",
        "dateOfFlight": "2016.10.23 20:22"
      }
    ]
  },
  "r": {
    "passengerRecords": [
      {
        "recordID": "TcZl048739",
        "passenger": {
          "firstName": "RkldU",
          "lastName": "rgS",
          "address": "azAcarnm",
          "phoneNumber": "9863026766"
        },
        "destination": "Montreal",
        "flightClass": "business",
        "dateOfFlight": "2016.11.18 10:10"
      }
    ]
  },
  "q": {
    "passengerRecords": [
      {
        "recordID": "tEvD110194",
        "passenger": {
          "firstName": "LTPSR",
          "lastName": "qdn",
          "address": "ogIgWQlg",
          "phoneNumber": "7475190775"
        },
        "destination": "NewDelhi",
        "flightClass": "fit",
        "dateOfFlight": "2016.10.23 20:22"
      },
      {
        "recordID": "bIuo970183",
        "passenger": {
          "firstName": "janksfa\u0027s",
          "lastName": "qfasdf",
          "address": "wfdsfa",
          "phoneNumber": "asdf"
        },
        "destination": "NewDelhi",
        "flightClass": "business",
        "dateOfFlight": "2016.10.23 20:22"
      }
    ]
  },
  "p": {
    "passengerRecords": [
      {
        "recordID": "Iwyv922603",
        "passenger": {
          "firstName": "iNYur",
          "lastName": "pNQ",
          "address": "UPiJfAct",
          "phoneNumber": "6099492443"
        },
        "destination": "Montreal",
        "flightClass": "business",
        "dateOfFlight": "2016.11.18 10:10"
      },
      {
        "recordID": "QRYF523613",
        "passenger": {
          "firstName": "HhokG",
          "lastName": "PIg",
          "address": "vqeAmixM",
          "phoneNumber": "9216417316"
        },
        "destination": "Montreal",
        "flightClass": "business",
        "dateOfFlight": "2016.08.08 07:07"
      }
    ]
  },
  "z": {
    "passengerRecords": [
      {
        "recordID": "iVlO546734",
        "passenger": {
          "firstName": "ZVhYx",
          "lastName": "ZZX",
          "address": "HKsREjrb",
          "phoneNumber": "1359327163"
        },
        "destination": "NewDelhi",
        "flightClass": "business",
        "dateOfFlight": "2016.10.23 20:22"
      },
      {
        "recordID": "kdjG332932",
        "passenger": {
          "firstName": "qeXVd",
          "lastName": "zrt",
          "address": "AnJAgMVX",
          "phoneNumber": "6627253982"
        },
        "destination": "Montreal",
        "flightClass": "business",
        "dateOfFlight": "2016.11.18 10:10"
      },
      {
        "recordID": "ALkW387796",
        "passenger": {
          "firstName": "OWuMt",
          "lastName": "Zbr",
          "address": "KQCJmllp",
          "phoneNumber": "7856671423"
        },
        "destination": "Montreal",
        "flightClass": "economy",
        "dateOfFlight": "2016.11.18 10:10"
      }
    ]
  },
  "x": {
    "passengerRecords": [
      {
        "recordID": "FzOz747681",
        "passenger": {
          "firstName": "cFJQG",
          "lastName": "XzC",
          "address": "fKiAoGdA",
          "phoneNumber": "1911673759"
        },
        "destination": "NewDelhi",
        "flightClass": "economy",
        "dateOfFlight": "2016.10.23 20:22"
      },
      {
        "recordID": "bmCM568034",
        "passenger": {
          "firstName": "doPzA",
          "lastName": "xYB",
          "address": "cdoxxDDW",
          "phoneNumber": "7000351500"
        },
        "destination": "Montreal",
        "flightClass": "economy",
        "dateOfFlight": "2016.11.18 10:10"
      }
    ]
  }
}